setup.cfg
setup.py
twitchist/__init__.py
twitchist.egg-info/PKG-INFO
twitchist.egg-info/SOURCES.txt
twitchist.egg-info/dependency_links.txt
twitchist.egg-info/entry_points.txt
twitchist.egg-info/not-zip-safe
twitchist.egg-info/requires.txt
twitchist.egg-info/top_level.txt