Metadata-Version: 1.0
Name: twitchist
Version: 0.2.4
Summary: A little tool that parse and show the streams from twitch.tv. Open it with you favorite browser or livestreamer.
Home-page: https://github.com/kursion/twitchist
Author: Yves Lange
Author-email: kursion@gmail.com
License: MIT
Platform: UNKNOWN
